pygl2d
