Metadata-Version: 1.0
Name: PyGL2D
Version: 0.3.6
Summary: A 2D Graphics Library for PyGame and PyOpenGL.
Home-page: https://github.com/RyanHope/PyGL2D
Author: Ryan Hope
Author-email: rmh3093@gmail.com
License: GPL-3
Platform: UNKNOWN
Classifier: License :: OSI Approved :: GNU General Public License (GPL)
Classifier: Framework :: Twisted
Classifier: Programming Language :: Python :: 2
Classifier: Topic :: Software Development :: Libraries :: pygame
Classifier: Topic :: Multimedia :: Graphics :: 3D Rendering
